mruntools/__init__.py
mruntools/config.py
mruntools/console.py
mruntools/data.py
mruntools/run.py
mruntools/spec.py
mruntools-0.1.0.dist-info/WHEEL
mruntools-0.1.0.dist-info/METADATA
mruntools-0.1.0.dist-info/RECORD
