Metadata-Version: 2.1
Name: mruntools
Version: 0.1.0
Summary: 
Author: Matthew Hartley
Author-email: mhartley@cantab.net
Requires-Python: >=3.8,<4.0
Classifier: Programming Language :: Python :: 3
Classifier: Programming Language :: Python :: 3.8
Requires-Dist: click (>=7.1.2,<8.0.0)
Requires-Dist: pandas (>=1.2.1,<2.0.0)
Requires-Dist: parse (>=1.19.0,<2.0.0)
Requires-Dist: ruamel.yaml (>=0.16.12,<0.17.0)
